abstract_apis/__init__.py
abstract_apis/async_make_request.py
abstract_apis/endpoint_utils.py
abstract_apis/make_request.py
abstract_apis/request_utils.py
abstract_apis/rpcCalls.py
abstract_apis-0.0.1.137.dist-info/METADATA
abstract_apis-0.0.1.137.dist-info/WHEEL
abstract_apis-0.0.1.137.dist-info/top_level.txt
abstract_apis-0.0.1.137.dist-info/RECORD
