Metadata-Version: 2.4
Name: abstract_apis
Version: 0.0.1.137
Summary: The `abstract_apis` module is designed to facilitate HTTP requests in Python applications, particularly those that require handling JSON data, dealing with custom API endpoints, and parsing complex nested JSON responses. The module simplifies request handling by abstracting away common tasks such as header management, URL construction, and response parsing.
Home-page: https://github.com/AbstractEndeavors/abstract_ide
Author: putkoff
Author-email: partners@abstractendeavors.com
Classifier: Development Status :: 3 - Alpha
Classifier: Intended Audience :: Developers
Classifier: License :: OSI Approved :: MIT License
Classifier: Programming Language :: Python :: 3
Classifier: Programming Language :: Python :: 3.11
Requires-Python: >=3.6
Requires-Dist: abstract_utilities
Requires-Dist: requests
Dynamic: author
Dynamic: author-email
Dynamic: classifier
Dynamic: description
Dynamic: description-content-type
Dynamic: home-page
Dynamic: requires-dist
Dynamic: requires-python
Dynamic: summary
